hydraMPP/__init__.py
hydraMPP/client.py
hydraMPP/host.py
hydraMPP/log.py
hydraMPP/net.py
hydraMPP-0.0.3.data/scripts/hydra-status.py
hydraMPP-0.0.3.dist-info/LICENSE.txt
hydraMPP-0.0.3.dist-info/METADATA
hydraMPP-0.0.3.dist-info/WHEEL
hydraMPP-0.0.3.dist-info/top_level.txt
hydraMPP-0.0.3.dist-info/RECORD
