Metadata-Version: 2.1
Name: hydraMPP
Version: 0.0.3
Summary: A simple class for Distributed Computing
Home-page: https://github.com/raw-lab/hydraMPP
Author: Jose L. Figueroa III
Author-email: jlfiguer@charlotte.edu
License: BSD License
Platform: Unix
Classifier: Programming Language :: Python :: 3
Classifier: Programming Language :: Python :: 3.6
Classifier: Programming Language :: Python :: 3.7
Classifier: Programming Language :: Python :: 3.8
Classifier: Programming Language :: Python :: 3.9
Classifier: Programming Language :: Python :: 3.10
Classifier: Programming Language :: Python :: 3.11
Classifier: Programming Language :: Python :: 3.12
Classifier: License :: OSI Approved :: BSD License
Classifier: Operating System :: Unix
Requires-Python: >=3.6
License-File: LICENSE.txt
Requires-Dist: setuptools
Requires-Dist: psutil
